nortech_internal/__init__.py
nortech_internal/derivers/__init__.py
nortech_internal/derivers/gateways/__init__.py
nortech_internal/derivers/gateways/muninn.py
nortech_internal/derivers/gateways/producer.py
nortech_internal/derivers/handlers/__init__.py
nortech_internal/derivers/handlers/deriver.py
nortech_internal/derivers/handlers/flow.py
nortech_internal/derivers/handlers/main.py
nortech_internal/derivers/repositories/Processor.py
nortech_internal/derivers/repositories/SQL.py
nortech_internal/derivers/repositories/TimeBucketJoin.py
nortech_internal/derivers/repositories/__init__.py
nortech_internal/derivers/repositories/data_db.py
nortech_internal/derivers/services/__init__.py
nortech_internal/derivers/services/instance.py
nortech_internal/derivers/services/logger.py
nortech_internal/derivers/services/metrics.py
nortech_internal/derivers/services/operators.py
nortech_internal/derivers/services/schema.py
nortech_internal/derivers/services/visualize.py
nortech_internal/derivers/values/__init__.py
nortech_internal/derivers/values/instance.py
nortech_internal/derivers/values/metrics.py
nortech_internal/derivers/values/physical_units.py
nortech_internal/derivers/values/physical_units_schema.py
nortech_internal/derivers/values/schema.py
nortech_python-0.0.3.dist-info/METADATA
nortech_python-0.0.3.dist-info/WHEEL
nortech_python-0.0.3.dist-info/RECORD
